README.txt
setup.py
nround/__init__.py
nround/nround.py
nround.egg-info/PKG-INFO
nround.egg-info/SOURCES.txt
nround.egg-info/dependency_links.txt
nround.egg-info/top_level.txt