Metadata-Version: 1.0
Name: nround
Version: 1.0
Summary: UNKNOWN
Home-page: https://github.com/usernameisalreadytaken4/nround
Author: Roman Bobrovskiy
Author-email: romul1988@gmail.com
License: UNKNOWN
Platform: UNKNOWN
